ac_websocket_client/__init__.py
ac_websocket_client/__main__.py
ac_websocket_client/app.py
ac_websocket_client/connection.py
ac_websocket_client/console.py
ac_websocket_client/constants.py
ac_websocket_client/driver.py
ac_websocket_client/entry_list.py
ac_websocket_client/objects.py
ac_websocket_client/server.py
ac_websocket_client/tracker.py
ac_websocket_server/__init__.py
ac_websocket_server/__main__.py
ac_websocket_server/child.py
ac_websocket_server/configuration.py
ac_websocket_server/connection.py
ac_websocket_server/constants.py
ac_websocket_server/debug.py
ac_websocket_server/dummy.py
ac_websocket_server/entries.py
ac_websocket_server/error.py
ac_websocket_server/game.py
ac_websocket_server/grid.py
ac_websocket_server/handlers.py
ac_websocket_server/lobby.py
ac_websocket_server/messages.py
ac_websocket_server/objects.py
ac_websocket_server/observer.py
ac_websocket_server/protocol.py
ac_websocket_server/server.py
ac_websocket_server/task_logger.py
ac_websocket_server/tracker.py
ac_websocket_server/watcher.py
ac_websocket_server-0.7.dev25.dist-info/METADATA
ac_websocket_server-0.7.dev25.dist-info/WHEEL
ac_websocket_server-0.7.dev25.dist-info/top_level.txt
ac_websocket_server-0.7.dev25.dist-info/RECORD
