Metadata-Version: 2.1
Name: ac-websocket-server
Version: 0.7.dev25
Summary: Assetto Corsa Websockets Server
Author: Mark Hannon
Author-email: mark.hannon@gmail.com
License: MIT
Classifier: Programming Language :: Python :: 3.9
Requires-Dist: aiofiles
Requires-Dist: aiohttp
Requires-Dist: psutil
Requires-Dist: websockets
